{"enemy_id": "terranbot-ai", "py/object": "sharpy.tools.opponent_data.OpponentData", "results": [{"build_used": "", "enemy_build": 0, "enemy_macro_build": 0, "enemy_race": {"py/reduce": [{"py/type": "sc2.data.Race"}, {"py/tuple": [4]}]}, "first_attacked": null, "game_duration": 0.0, "game_started": "2021-05-10T14:52:08.459324", "guid": {"hex": "e4a1eb3a5f19436ea520c6ba62f8dffb", "py/object": "uuid.UUID"}, "my_race": {"py/reduce": [{"py/type": "sc2.data.Race"}, {"py/tuple": [1]}]}, "py/object": "sharpy.tools.opponent_data.GameResult", "result": -1}, {"build_used": "", "enemy_build": 0, "enemy_macro_build": 0, "enemy_race": {"py/id": 3}, "first_attacked": null, "game_duration": 0.0, "game_started": "2021-05-10T14:53:44.343077", "guid": {"hex": "f6aa65fde1ca4c6ca498eb40bc096980", "py/object": "uuid.UUID"}, "my_race": {"py/id": 5}, "py/object": "sharpy.tools.opponent_data.GameResult", "result": -1}, {"build_used": "", "enemy_build": 0, "enemy_macro_build": 0, "enemy_race": {"py/id": 3}, "first_attacked": null, "game_duration": 0.0, "game_started": "2021-05-10T15:32:13.540027", "guid": {"hex": "885bcc4ad0b84ae2b574aa71804304d9", "py/object": "uuid.UUID"}, "my_race": {"py/id": 5}, "py/object": "sharpy.tools.opponent_data.GameResult", "result": -1}, {"build_used": "", "enemy_build": 0, "enemy_macro_build": 0, "enemy_race": {"py/id": 3}, "first_attacked": null, "game_duration": 0.0, "game_started": "2021-05-12T13:09:02.867088", "guid": {"hex": "aa94291677734fdf84dd71838e825e6b", "py/object": "uuid.UUID"}, "my_race": {"py/id": 5}, "py/object": "sharpy.tools.opponent_data.GameResult", "result": -1}, {"build_used": "", "enemy_build": 0, "enemy_macro_build": 0, "enemy_race": {"py/id": 3}, "first_attacked": null, "game_duration": 0.0, "game_started": "2021-05-12T13:10:52.695096", "guid": {"hex": "b80773787e9d42278092287183c283f1", "py/object": "uuid.UUID"}, "my_race": {"py/id": 5}, "py/object": "sharpy.tools.opponent_data.GameResult", "result": -1}, {"build_used": "", "enemy_build": 0, "enemy_macro_build": 0, "enemy_race": {"py/id": 3}, "first_attacked": null, "game_duration": 295.5357142857143, "game_started": "2021-05-12T13:24:51.694778", "guid": {"hex": "c93978a896474654a822fdf4890a1ef6", "py/object": "uuid.UUID"}, "my_race": {"py/id": 5}, "py/object": "sharpy.tools.opponent_data.GameResult", "result": 1}, {"build_used": "", "enemy_build": 0, "enemy_macro_build": 0, "enemy_race": {"py/id": 3}, "first_attacked": null, "game_duration": 0.0, "game_started": "2021-05-12T14:11:37.565348", "guid": {"hex": "ecdd34ee92ff47dd84e49583c09ac071", "py/object": "uuid.UUID"}, "my_race": {"py/id": 5}, "py/object": "sharpy.tools.opponent_data.GameResult", "result": -1}, {"build_used": "", "enemy_build": 0, "enemy_macro_build": 0, "enemy_race": {"py/id": 3}, "first_attacked": 259.2857142857143, "game_duration": 323.2142857142857, "game_started": "2021-05-12T14:25:01.069863", "guid": {"hex": "fc5e8ce333c44e9085b52bd9e6730b41", "py/object": "uuid.UUID"}, "my_race": {"py/id": 5}, "py/object": "sharpy.tools.opponent_data.GameResult", "result": -1}, {"build_used": "", "enemy_build": 0, "enemy_macro_build": 0, "enemy_race": {"py/id": 3}, "first_attacked": null, "game_duration": 0.0, "game_started": "2021-05-12T14:43:28.012290", "guid": {"hex": "303bf5bfd6ae4d34b486084463445a2d", "py/object": "uuid.UUID"}, "my_race": {"py/id": 5}, "py/object": "sharpy.tools.opponent_data.GameResult", "result": -1}, {"build_used": "", "enemy_build": 0, "enemy_macro_build": 0, "enemy_race": {"py/id": 3}, "first_attacked": null, "game_duration": 0.0, "game_started": "2021-05-12T15:01:35.510148", "guid": {"hex": "0236a4a35d6b4f35a07344be8861310c", "py/object": "uuid.UUID"}, "my_race": {"py/id": 5}, "py/object": "sharpy.tools.opponent_data.GameResult", "result": -1}]}